[
    { "id": 1, "name": "Administrasi Perkantoran" },
    { "id": 2, "name": "Hubungan Masyarakat" },
    { "id": 3, "name": "Perpustakaan" },
    { "id": 4, "name": "Ilmu Administrasi Bisnis" },
    { "id": 5, "name": "Ilmu Administrasi Negara" },
    { "id": 6, "name": "Ilmu Komunikasi" },
    { "id": 7, "name": "Ilmu Pemerintahan" },
    { "id": 8, "name": "Sosiologi" },
    { "id": 9, "name": "Akuntansi" },
    { "id": 10, "name": "Akuntansi PSDKU Way Kanan" },
    { "id": 11, "name": "Keuangan dan Perbankan" },
    { "id": 12, "name": "Manajemen Pemasaran" },
    { "id": 13, "name": "Perbankan dan Keuangan PSDKU Lampung Tengah" },
    { "id": 14, "name": "Perpajakan" },
    { "id": 15, "name": "Bisnis Digital" },
    { "id": 16, "name": "Ekonomi Pembangunan" },
    { "id": 17, "name": "Manajemen" },
    { "id": 18, "name": "Manajemen Informatika" },
    { "id": 19, "name": "Biologi" },
    { "id": 20, "name": "Biologi Terapan" },
    { "id": 21, "name": "Fisika" },
    { "id": 22, "name": "Ilmu Komputer" },
    { "id": 23, "name": "Ilmu Komputer PSDKU Way Kanan" },
    { "id": 24, "name": "Kimia" },
    { "id": 25, "name": "Matematika" },
    { "id": 26, "name": "Sistem Informasi" },
    { "id": 27, "name": "Perkebunan" },
    { "id": 28, "name": "Agribisnis" },
    { "id": 29, "name": "Agronomi" },
    { "id": 30, "name": "Agroteknologi" },
    { "id": 31, "name": "Budidaya Perairan" },
    { "id": 32, "name": "Ilmu Kelautan" },
    { "id": 33, "name": "Ilmu Tanah" },
    { "id": 34, "name": "Kehutanan" },
    { "id": 35, "name": "Nutrisi dan Teknologi Pakan Ternak" },
    { "id": 36, "name": "Penyuluhan Pertanian" },
    { "id": 37, "name": "Peternakan" },
    { "id": 38, "name": "Proteksi Tanaman" },
    { "id": 39, "name": "Sumberdaya Akuatik" },
    { "id": 40, "name": "Teknologi Hasil Pertanian" },
    { "id": 41, "name": "Teknologi Industri Pertanian" },
    { "id": 42, "name": "Teknik Pertanian" },
    { "id": 43, "name": "Teknik Mesin" },
    { "id": 44, "name": "Teknik Sipil" },
    { "id": 45, "name": "Teknik Survey dan Pemetaan" },
    { "id": 46, "name": "Arsitektur" },
    { "id": 47, "name": "Teknik Elektro" },
    { "id": 48, "name": "Teknik Geodesi" },
    { "id": 49, "name": "Teknik Geofisika" },
    { "id": 50, "name": "Teknik Geologi" },
    { "id": 51, "name": "Teknik Informatika" },
    { "id": 52, "name": "Teknik Kimia" },
    { "id": 53, "name": "Teknik Lingkungan" },
    { "id": 54, "name": "Teknologi Rekayasa Otomotif" },
    { "id": 55, "name": "Ilmu Hukum" },
    { "id": 56, "name": "Bimbingan dan Konseling" },
    { "id": 57, "name": "Pendidikan Bahasa dan Sastra Indonesia" },
    { "id": 58, "name": "Pendidikan Bahasa Inggris" },
    { "id": 59, "name": "Pendidikan Bahasa Lampung" },
    { "id": 60, "name": "Pendidikan Bahasa Perancis" },
    { "id": 61, "name": "Pendidikan Biologi" },
    { "id": 62, "name": "Pendidikan Ekonomi" },
    { "id": 63, "name": "Pendidikan Fisika" },
    { "id": 64, "name": "Pendidikan Geografi" },
    { "id": 65, "name": "Pendidikan Guru Pendidikan Anak Usia Dini" },
    { "id": 66, "name": "Pendidikan Guru Sekolah Dasar" },
    { "id": 67, "name": "Pendidikan Jasmani" },
    { "id": 68, "name": "Pendidikan Kimia" },
    { "id": 69, "name": "Pendidikan Matematika" },
    { "id": 70, "name": "Pendidikan Musik" },
    { "id": 71, "name": "Pendidikan Pancasila dan Kewarganegaraan" },
    { "id": 72, "name": "Pendidikan Sejarah" },
    { "id": 73, "name": "Pendidikan Tari" },
    { "id": 74, "name": "Pendidikan Teknologi Informasi" },
    { "id": 75, "name": "Farmasi" },
    { "id": 76, "name": "Kedokteran" },
    { "id": 77, "name": "Gizi" }
]
